{"1.11.1-1": ["Tue Dec 23 2025", "Dharini Dutia", "dharini@openrobotics.org"], "1.11.0-1": ["Thu Apr 24 2025", "Dharini Dutia", "dharini@openrobotics.org"], "1.10.2-2": ["Tue Apr 22 2025", "Dharini Dutia", "dharini@openrobotics.org"], "1.10.2-1": ["Thu Apr 17 2025", "Dharini Dutia", "dharini@openrobotics.org"], "1.10.1-1": ["Wed Nov 20 2024", "Dharini Dutia", "dharini@openrobotics.org"], "1.10.0-1": ["Thu Oct 03 2024", "Dharini Dutia", "dharini@openrobotics.org"], "1.9.0-1": ["Fri Apr 26 2024", "Dharini Dutia", "dharini@openrobotics.org"], "1.8.0-1": ["Thu Mar 28 2024", "Dharini Dutia", "dharini@openrobotics.org"], "1.7.0-2": ["Tue Mar 05 2024", "Dharini Dutia", "dharini@openrobotics.org"]}